<?xml version="1.0" encoding="UTF-8"?>
<panorama apprev="18080" id="node1" appversion="6.1.13">
  <input width="2224" levelingpitch="0" height="2224" overlap="1" levelingroll="0" levelbiashidpi="1.000" leveltilesize="510" leveltileurl="tiles/node1/cf_%c/l_%l/c_%x/tile_%y.jpg" levelbias="0.400">
    <level preload="0" width="2224" height="2224" predecode="0"/>
    <level preload="0" width="1112" height="1112" predecode="0"/>
    <level preload="0" width="556" height="556" predecode="0"/>
    <level preload="1" width="278" height="278" predecode="1"/>
    <preview strip="1" color="0x808080"/>
  </input>
  <view pannorth="0" fovmode="0">
    <start tilt="0" pan="0" fov="70" projection="4"/>
    <flyin tilt="-90" pan="0" fov="170" projection="9"/>
    <min tilt="-90" pan="0" fovpixel="2"/>
    <max fovstereographic="270" tilt="90" pan="360" fovfisheye="360" fov="120" scaletofit="1"/>
  </view>
  <userdata tags="PANOS" datetime="" longitude="-111.65444000" customnodeid="" source="" comment="" info="" copyright="" latitude="40.11266000" title="Spanish Fork Memorial Square" description="Memorial Square Park on Main Street in Spanish Fork Utah" author="Cam Stephens" nodeid="node1" heading="0"/>
  <hotspots wordwrap="1" width="180" height="20">
    <label background="1" wordwrap="1" enabled="1" backgroundalpha="1" width="180" height="20" textcolor="0x000000" backgroundcolor="0xffffff" textalpha="1" bordercolor="0x000000" borderalpha="1" border="1" borderradius="1"/>
    <polystyle backgroundalpha="0.25098" backgroundcolor="0x0000ff" bordercolor="0x0000ff" handcursor="1" borderalpha="1" mode="0"/>
    <hotspot skinid="ht_image" tilt="-12.91" pan="-149.93" url="images/Crib.png" id="Point01" target="" title="" description=""/>
  </hotspots>
  <media/>
  <transition enabled="1" zoomfov="20" zoomin="0" zoomafterinfov="90" zoomspeed="2" zoomout="0" zoomoutpause="1" softedge="0" blendtime="1" blendcolor="0x000000" zoomafteroutfov="20" type="crossdissolve"/>
  <animation useinautorotation="0" animsequence="Animation01" syncanimationwithvideo="0"/>
  <control lockedkeyboard="0" sensitivity="8" simulatemass="1" lockedmouse="0" rubberband="0" invertwheel="0" speedwheel="1" contextfullscreen="1" contextvr="1" invertcontrol="1" dblclickfullscreen="0" lockedwheel="0" contextprojections="0" lockedkeyboardzoom="0"/>
</panorama>
